{
    "Ar36": {
        "error": 0.000858936106165971, 
        "filter_outliers_dict": {
            "filter_outliers": true, 
            "iterations": 1, 
            "std_devs": 2
        }, 
        "fit": "Linear", 
        "value": 0.01316584095368254
    }, 
    "Ar37": {
        "error": 0.023553826163014276, 
        "filter_outliers_dict": {
            "filter_outliers": true, 
            "iterations": 1, 
            "std_devs": 2
        }, 
        "fit": "linear", 
        "value": 0.06148075450673499
    }, 
    "Ar38": {
        "error": 0.013838108432464438, 
        "filter_outliers_dict": {
            "filter_outliers": true, 
            "iterations": 1, 
            "std_devs": 2
        }, 
        "fit": "linear", 
        "value": 0.039745375820179125
    }, 
    "Ar39": {
        "error": 0.040818543113015145, 
        "filter_outliers_dict": {
            "filter_outliers": true, 
            "iterations": 1, 
            "std_devs": 2
        }, 
        "fit": "Linear", 
        "value": 0.5266276103902181
    }, 
    "Ar40": {
        "error": 0.09345529498218784, 
        "filter_outliers_dict": {
            "filter_outliers": true, 
            "iterations": 1, 
            "std_devs": 2
        }, 
        "fit": "Linear", 
        "value": 447.5244673458119
    }, 
    "Ar41": {
        "error": 0.01000287767920568, 
        "filter_outliers_dict": {
            "filter_outliers": true, 
            "iterations": 1, 
            "std_devs": 2
        }, 
        "fit": "Average", 
        "value": -0.0030024920279933982
    }
}