{
    "Ar36":{
        "error":0.0001895894,
        "error_type":"",
        "fit":"previous",
        "references":[
            {
                "exclude":false,
                "record_id":"bu-FC-J-8602"
            }
        ],
        "value":0.0033249805
    },
    "Ar37":{
        "error":0.0045807553,
        "error_type":"",
        "fit":"previous",
        "references":[
            {
                "exclude":false,
                "record_id":"bu-FC-J-8602"
            }
        ],
        "value":0.0427719169
    },
    "Ar38":{
        "error":0.002228405,
        "error_type":"",
        "fit":"previous",
        "references":[
            {
                "exclude":false,
                "record_id":"bu-FC-J-8602"
            }
        ],
        "value":0.0045221051
    },
    "Ar39":{
        "error":0.0095013826,
        "error_type":"",
        "fit":"previous",
        "references":[
            {
                "exclude":false,
                "record_id":"bu-FC-J-8602"
            }
        ],
        "value":0.0308935553
    },
    "Ar40":{
        "error":0.0125202845,
        "error_type":"",
        "fit":"previous",
        "references":[
            {
                "exclude":false,
                "record_id":"bu-FC-J-8602"
            }
        ],
        "value":0.5844764509
    },
    "Ar41":{
        "error":0.0119260649,
        "error_type":"",
        "fit":"previous",
        "references":[
            {
                "exclude":false,
                "record_id":"bu-FC-J-8602"
            }
        ],
        "value":-0.0114461561
    }
}