{
    "AX": {
        "error": 0.004665570432494874, 
        "filter_outliers_dict": {
            "filter_outliers": true, 
            "iterations": 1, 
            "std_devs": 2
        }, 
        "fit": "average", 
        "value": 0.13451964484199358
    }, 
    "CDD": {
        "error": 4.775732315275081e-06, 
        "filter_outliers_dict": {
            "filter_outliers": true, 
            "iterations": 1, 
            "std_devs": 10
        }, 
        "fit": "average", 
        "value": 1.4834510538163448e-05
    }, 
    "H1": {
        "error": 0.003327530387258902, 
        "filter_outliers_dict": {
            "filter_outliers": true, 
            "iterations": 1, 
            "std_devs": 2
        }, 
        "fit": "average", 
        "value": 0.09325363803245522
    }, 
    "H2": {
        "error": 0.002962919370191519, 
        "filter_outliers_dict": {
            "filter_outliers": true, 
            "iterations": 1, 
            "std_devs": 2
        }, 
        "fit": "average", 
        "value": -0.08898347314144733
    }, 
    "L1": {
        "error": 0.0017457146786571515, 
        "filter_outliers_dict": {
            "filter_outliers": true, 
            "iterations": 1, 
            "std_devs": 2
        }, 
        "fit": "average", 
        "value": -0.024239896500894722
    }, 
    "L2": {
        "error": 0.004289319508543951, 
        "filter_outliers_dict": {
            "filter_outliers": true, 
            "iterations": 1, 
            "std_devs": 2
        }, 
        "fit": "average", 
        "value": -0.0059333178144712435
    }
}