{
    "AX": {
        "error": 0.00897877826515891, 
        "filter_outliers_dict": {
            "filter_outliers": true, 
            "iterations": 1, 
            "std_devs": 2
        }, 
        "fit": "average", 
        "value": 0.11989367948624519
    }, 
    "CDD": {
        "error": 2.6815725226359174e-05, 
        "filter_outliers_dict": {
            "filter_outliers": true, 
            "iterations": 1, 
            "std_devs": 10
        }, 
        "fit": "average", 
        "value": 0.00018172275570765175
    }, 
    "H1": {
        "error": 0.007000655174210235, 
        "filter_outliers_dict": {
            "filter_outliers": true, 
            "iterations": 1, 
            "std_devs": 2
        }, 
        "fit": "average", 
        "value": 0.08260962636774599
    }, 
    "H2": {
        "error": 0.005231873785704991, 
        "filter_outliers_dict": {
            "filter_outliers": true, 
            "iterations": 1, 
            "std_devs": 2
        }, 
        "fit": "average", 
        "value": -0.09388159390347675
    }, 
    "L1": {
        "error": 0.002964524638662042, 
        "filter_outliers_dict": {
            "filter_outliers": true, 
            "iterations": 1, 
            "std_devs": 2
        }, 
        "fit": "average", 
        "value": -0.017720843140625473
    }, 
    "L2": {
        "error": 0.0078363556802893, 
        "filter_outliers_dict": {
            "filter_outliers": true, 
            "iterations": 1, 
            "std_devs": 2
        }, 
        "fit": "average", 
        "value": 0.00038717290452949094
    }
}