{
    "AX": {
        "error": 0.009326882361605419, 
        "filter_outliers_dict": {
            "filter_outliers": true, 
            "iterations": 1, 
            "std_devs": 2
        }, 
        "fit": "average", 
        "value": 0.16125229221291892
    }, 
    "CDD": {
        "error": 2.1213204018607613e-05, 
        "filter_outliers_dict": {
            "filter_outliers": true, 
            "iterations": 1, 
            "std_devs": 10
        }, 
        "fit": "average", 
        "value": 0.00014092785072560222
    }, 
    "H1": {
        "error": 0.0073220515237875676, 
        "filter_outliers_dict": {
            "filter_outliers": true, 
            "iterations": 1, 
            "std_devs": 2
        }, 
        "fit": "average", 
        "value": 0.09955864192708307
    }, 
    "H2": {
        "error": 0.005829049399392063, 
        "filter_outliers_dict": {
            "filter_outliers": true, 
            "iterations": 1, 
            "std_devs": 2
        }, 
        "fit": "average", 
        "value": -0.08410063328572569
    }, 
    "L1": {
        "error": 0.0035743734397809127, 
        "filter_outliers_dict": {
            "filter_outliers": true, 
            "iterations": 1, 
            "std_devs": 2
        }, 
        "fit": "average", 
        "value": -0.049821173179317974
    }, 
    "L2": {
        "error": 0.007747296569451732, 
        "filter_outliers_dict": {
            "filter_outliers": true, 
            "iterations": 1, 
            "std_devs": 2
        }, 
        "fit": "average", 
        "value": -0.0009727119878961773
    }
}